[
    {
        "Id": "66b6a1010000000000000000",
        "Name": "Adidas Shoes Shoe 1",
        "Description": "High quality Adidas shoes designed for performance.",
        "Price": 3050,
        "ImageFile": "images/products/adidas_shoe-1.png",
        "Summary": "Adidas Shoes for professionals.",
        "Types": {
            "Id": "63ca5d4bc3a8a58f47299f97",
            "Name": "Shoes"
        },
        "Brands": {
            "Id": "63ca5e40e0aa3968b549af53",
            "Name": "Adidas"
        }
    },
    {
        "Id": "66b6a1020000000000000000",
        "Name": "Adidas Football Football 1",
        "Description": "High quality Adidas football ideal for matches.",
        "Price": 1250,
        "ImageFile": "images/products/adidas_football-1.png",
        "Summary": "Adidas Football for professionals.",
        "Types": {
            "Id": "63ca5d7d380402dce7f06ebc",
            "Name": "Football"
        },
        "Brands": {
            "Id": "63ca5e40e0aa3968b549af53",
            "Name": "Adidas"
        }
    },
    {
        "Id": "66b6a1030000000000000000",
        "Name": "Adidas Shoes Shoe 2",
        "Description": "High quality Adidas shoes designed for performance.",
        "Price": 3100,
        "ImageFile": "images/products/adidas_shoe-2.png",
        "Summary": "Adidas Shoes for professionals.",
        "Types": {
            "Id": "63ca5d4bc3a8a58f47299f97",
            "Name": "Shoes"
        },
        "Brands": {
            "Id": "63ca5e40e0aa3968b549af53",
            "Name": "Adidas"
        }
    },
    {
        "Id": "66b6a1040000000000000000",
        "Name": "Adidas Football Football 2",
        "Description": "High quality Adidas football ideal for matches.",
        "Price": 1300,
        "ImageFile": "images/products/adidas_football-2.png",
        "Summary": "Adidas Football for professionals.",
        "Types": {
            "Id": "63ca5d7d380402dce7f06ebc",
            "Name": "Football"
        },
        "Brands": {
            "Id": "63ca5e40e0aa3968b549af53",
            "Name": "Adidas"
        }
    },
    {
        "Id": "66b6a1050000000000000000",
        "Name": "Adidas Shoes Shoe 3",
        "Description": "High quality Adidas shoes designed for performance.",
        "Price": 3150,
        "ImageFile": "images/products/adidas_shoe-3.png",
        "Summary": "Adidas Shoes for professionals.",
        "Types": {
            "Id": "63ca5d4bc3a8a58f47299f97",
            "Name": "Shoes"
        },
        "Brands": {
            "Id": "63ca5e40e0aa3968b549af53",
            "Name": "Adidas"
        }
    },
    {
        "Id": "66b6a1060000000000000000",
        "Name": "Adidas Football Football 3",
        "Description": "High quality Adidas football ideal for matches.",
        "Price": 1350,
        "ImageFile": "images/products/adidas_football-3.png",
        "Summary": "Adidas Football for professionals.",
        "Types": {
            "Id": "63ca5d7d380402dce7f06ebc",
            "Name": "Football"
        },
        "Brands": {
            "Id": "63ca5e40e0aa3968b549af53",
            "Name": "Adidas"
        }
    },
    {
        "Id": "66b6a1070000000000000000",
        "Name": "ASICS Shoes Shoe 1",
        "Description": "High quality ASICS shoes built for comfort.",
        "Price": 2860,
        "ImageFile": "images/products/asics_shoe-1.png",
        "Summary": "ASICS Shoes for professionals.",
        "Types": {
            "Id": "63ca5d4bc3a8a58f47299f97",
            "Name": "Shoes"
        },
        "Brands": {
            "Id": "63ca5e4c455900b990b43bc1",
            "Name": "ASICS"
        }
    },
    {
        "Id": "66b6a1080000000000000000",
        "Name": "ASICS Shoes Shoe 2",
        "Description": "High quality ASICS shoes lightweight and durable.",
        "Price": 2915,
        "ImageFile": "images/products/asics_shoe-2.png",
        "Summary": "ASICS Shoes for professionals.",
        "Types": {
            "Id": "63ca5d4bc3a8a58f47299f97",
            "Name": "Shoes"
        },
        "Brands": {
            "Id": "63ca5e4c455900b990b43bc1",
            "Name": "ASICS"
        }
    },
    {
        "Id": "66b6a1090000000000000000",
        "Name": "ASICS Rackets Racket 1",
        "Description": "High quality ASICS rackets for powerful shots.",
        "Price": 1540,
        "ImageFile": "images/products/yonex-badminton-1.png",
        "Summary": "ASICS Rackets for professionals.",
        "Types": {
            "Id": "63ca5d6d958e43ee1cd375fe",
            "Name": "Rackets"
        },
        "Brands": {
            "Id": "63ca5e4c455900b990b43bc1",
            "Name": "ASICS"
        }
    },
    {
        "Id": "66b6a1100000000000000000",
        "Name": "ASICS Rackets Racket 2",
        "Description": "High quality ASICS rackets for precision play.",
        "Price": 1595,
        "ImageFile": "images/products/yonex-badminton-2.png",
        "Summary": "ASICS Rackets for professionals.",
        "Types": {
            "Id": "63ca5d6d958e43ee1cd375fe",
            "Name": "Rackets"
        },
        "Brands": {
            "Id": "63ca5e4c455900b990b43bc1",
            "Name": "ASICS"
        }
    },
    {
        "Id": "66b6a1110000000000000000",
        "Name": "ASICS Kit Bags Kit Bag 1",
        "Description": "High quality ASICS kit bags spacious and stylish.",
        "Price": 930,
        "ImageFile": "images/products/yonex-kitback-1.png",
        "Summary": "ASICS Kit Bags for professionals.",
        "Types": {
            "Id": "63ca5d8849bc19321b8be5f1",
            "Name": "Kit Bags"
        },
        "Brands": {
            "Id": "63ca5e4c455900b990b43bc1",
            "Name": "ASICS"
        }
    },
    {
        "Id": "66b6a1120000000000000000",
        "Name": "ASICS Kit Bags Kit Bag 2",
        "Description": "High quality ASICS kit bags durable material.",
        "Price": 985,
        "ImageFile": "images/products/babolat-kitback-3.png",
        "Summary": "ASICS Kit Bags for professionals.",
        "Types": {
            "Id": "63ca5d8849bc19321b8be5f1",
            "Name": "Kit Bags"
        },
        "Brands": {
            "Id": "63ca5e4c455900b990b43bc1",
            "Name": "ASICS"
        }
    },
    {
        "Id": "66b6a1130000000000000000",
        "Name": "Victor Shoes Shoe 2",
        "Description": "High quality Victor shoes built for comfort.",
        "Price": 2920,
        "ImageFile": "images/products/victor_shoe-2.png",
        "Summary": "Victor Shoes for professionals.",
        "Types": {
            "Id": "63ca5d4bc3a8a58f47299f97",
            "Name": "Shoes"
        },
        "Brands": {
            "Id": "63ca5e59065163c16451bd73",
            "Name": "Victor"
        }
    },
    {
        "Id": "66b6a1140000000000000000",
        "Name": "Victor Shoes Shoe 3",
        "Description": "High quality Victor shoes lightweight and durable.",
        "Price": 2980,
        "ImageFile": "images/products/victor_shoe-1.png",
        "Summary": "Victor Shoes for professionals.",
        "Types": {
            "Id": "63ca5d4bc3a8a58f47299f97",
            "Name": "Shoes"
        },
        "Brands": {
            "Id": "63ca5e59065163c16451bd73",
            "Name": "Victor"
        }
    },
    {
        "Id": "66b6a1150000000000000000",
        "Name": "Victor Rackets Racket 2",
        "Description": "High quality Victor rackets for powerful shots.",
        "Price": 1580,
        "ImageFile": "images/products/victor-racket-2.png",
        "Summary": "Victor Rackets for professionals.",
        "Types": {
            "Id": "63ca5d6d958e43ee1cd375fe",
            "Name": "Rackets"
        },
        "Brands": {
            "Id": "63ca5e59065163c16451bd73",
            "Name": "Victor"
        }
    },
    {
        "Id": "66b6a1160000000000000000",
        "Name": "Victor Rackets Racket 3",
        "Description": "High quality Victor rackets for precision play.",
        "Price": 1640,
        "ImageFile": "images/products/victor-racket-3.png",
        "Summary": "Victor Rackets for professionals.",
        "Types": {
            "Id": "63ca5d6d958e43ee1cd375fe",
            "Name": "Rackets"
        },
        "Brands": {
            "Id": "63ca5e59065163c16451bd73",
            "Name": "Victor"
        }
    },
    {
        "Id": "66b6a1170000000000000000",
        "Name": "Victor Kit Bags Kit Bag 2",
        "Description": "High quality Victor kit bags spacious and stylish.",
        "Price": 960,
        "ImageFile": "images/products/babolat-kitback-2.png",
        "Summary": "Victor Kit Bags for professionals.",
        "Types": {
            "Id": "63ca5d8849bc19321b8be5f1",
            "Name": "Kit Bags"
        },
        "Brands": {
            "Id": "63ca5e59065163c16451bd73",
            "Name": "Victor"
        }
    },
    {
        "Id": "66b6a1180000000000000000",
        "Name": "Victor Kit Bags Kit Bag 3",
        "Description": "High quality Victor kit bags durable material.",
        "Price": 1020,
        "ImageFile": "images/products/yonex-kitback-2.png",
        "Summary": "Victor Kit Bags for professionals.",
        "Types": {
            "Id": "63ca5d8849bc19321b8be5f1",
            "Name": "Kit Bags"
        },
        "Brands": {
            "Id": "63ca5e59065163c16451bd73",
            "Name": "Victor"
        }
    },
    {
        "Id": "66b6a1190000000000000000",
        "Name": "Yonex Shoes Shoe 3",
        "Description": "High quality Yonex shoes built for comfort.",
        "Price": 2980,
        "ImageFile": "images/products/yonex_shoe-3.png",
        "Summary": "Yonex Shoes for professionals.",
        "Types": {
            "Id": "63ca5d4bc3a8a58f47299f97",
            "Name": "Shoes"
        },
        "Brands": {
            "Id": "63ca5e655ec1fdc49bd9327d",
            "Name": "Yonex"
        }
    },
    {
        "Id": "66b6a1200000000000000000",
        "Name": "Yonex Shoes Shoe 4",
        "Description": "High quality Yonex shoes lightweight and durable.",
        "Price": 3045,
        "ImageFile": "images/products/yonex_shoe-1.png",
        "Summary": "Yonex Shoes for professionals.",
        "Types": {
            "Id": "63ca5d4bc3a8a58f47299f97",
            "Name": "Shoes"
        },
        "Brands": {
            "Id": "63ca5e655ec1fdc49bd9327d",
            "Name": "Yonex"
        }
    },
    {
        "Id": "66b6a1210000000000000000",
        "Name": "Yonex Rackets Racket 3",
        "Description": "High quality Yonex rackets for powerful shots.",
        "Price": 1620,
        "ImageFile": "images/products/yonex-racket-3.png",
        "Summary": "Yonex Rackets for professionals.",
        "Types": {
            "Id": "63ca5d6d958e43ee1cd375fe",
            "Name": "Rackets"
        },
        "Brands": {
            "Id": "63ca5e655ec1fdc49bd9327d",
            "Name": "Yonex"
        }
    },
    {
        "Id": "66b6a1220000000000000000",
        "Name": "Yonex Rackets Racket 4",
        "Description": "High quality Yonex rackets for precision play.",
        "Price": 1685,
        "ImageFile": "images/products/yonex-racket-1.png",
        "Summary": "Yonex Rackets for professionals.",
        "Types": {
            "Id": "63ca5d6d958e43ee1cd375fe",
            "Name": "Rackets"
        },
        "Brands": {
            "Id": "63ca5e655ec1fdc49bd9327d",
            "Name": "Yonex"
        }
    },
    {
        "Id": "66b6a1230000000000000000",
        "Name": "Yonex Kit Bags Kit Bag 3",
        "Description": "High quality Yonex kit bags spacious and stylish.",
        "Price": 990,
        "ImageFile": "images/products/yonex-kitback-3.png",
        "Summary": "Yonex Kit Bags for professionals.",
        "Types": {
            "Id": "63ca5d8849bc19321b8be5f1",
            "Name": "Kit Bags"
        },
        "Brands": {
            "Id": "63ca5e655ec1fdc49bd9327d",
            "Name": "Yonex"
        }
    },
    {
        "Id": "66b6a1240000000000000000",
        "Name": "Yonex Kit Bags Kit Bag 4",
        "Description": "High quality Yonex kit bags durable material.",
        "Price": 1055,
        "ImageFile": "images/products/yonex-kitback-1.png",
        "Summary": "Yonex Kit Bags for professionals.",
        "Types": {
            "Id": "63ca5d8849bc19321b8be5f1",
            "Name": "Kit Bags"
        },
        "Brands": {
            "Id": "63ca5e655ec1fdc49bd9327d",
            "Name": "Yonex"
        }
    },
    {
        "Id": "66b6a1250000000000000000",
        "Name": "Puma Shoes Shoe 4",
        "Description": "High quality Puma shoes built for comfort.",
        "Price": 3040,
        "ImageFile": "images/products/puma_shoe-1.png",
        "Summary": "Puma Shoes for professionals.",
        "Types": {
            "Id": "63ca5d4bc3a8a58f47299f97",
            "Name": "Shoes"
        },
        "Brands": {
            "Id": "63ca5e728c4cff9708ada2a6",
            "Name": "Puma"
        }
    },
    {
        "Id": "66b6a1260000000000000000",
        "Name": "Puma Shoes Shoe 5",
        "Description": "High quality Puma shoes lightweight and durable.",
        "Price": 3110,
        "ImageFile": "images/products/puma_shoe-2.png",
        "Summary": "Puma Shoes for professionals.",
        "Types": {
            "Id": "63ca5d4bc3a8a58f47299f97",
            "Name": "Shoes"
        },
        "Brands": {
            "Id": "63ca5e728c4cff9708ada2a6",
            "Name": "Puma"
        }
    },
    {
        "Id": "66b6a1270000000000000000",
        "Name": "Puma Rackets Racket 4",
        "Description": "High quality Puma rackets for powerful shots.",
        "Price": 1660,
        "ImageFile": "images/products/babolat-racket-1.png",
        "Summary": "Puma Rackets for professionals.",
        "Types": {
            "Id": "63ca5d6d958e43ee1cd375fe",
            "Name": "Rackets"
        },
        "Brands": {
            "Id": "63ca5e728c4cff9708ada2a6",
            "Name": "Puma"
        }
    },
    {
        "Id": "66b6a1280000000000000000",
        "Name": "Puma Rackets Racket 5",
        "Description": "High quality Puma rackets for precision play.",
        "Price": 1730,
        "ImageFile": "images/products/babolat-racket-2.png",
        "Summary": "Puma Rackets for professionals.",
        "Types": {
            "Id": "63ca5d6d958e43ee1cd375fe",
            "Name": "Rackets"
        },
        "Brands": {
            "Id": "63ca5e728c4cff9708ada2a6",
            "Name": "Puma"
        }
    },
    {
        "Id": "66b6a1290000000000000000",
        "Name": "Puma Kit Bags Kit Bag 4",
        "Description": "High quality Puma kit bags spacious and stylish.",
        "Price": 1020,
        "ImageFile": "images/products/yonex-kitback-1.png",
        "Summary": "Puma Kit Bags for professionals.",
        "Types": {
            "Id": "63ca5d8849bc19321b8be5f1",
            "Name": "Kit Bags"
        },
        "Brands": {
            "Id": "63ca5e728c4cff9708ada2a6",
            "Name": "Puma"
        }
    },
    {
        "Id": "66b6a1300000000000000000",
        "Name": "Puma Kit Bags Kit Bag 5",
        "Description": "High quality Puma kit bags durable material.",
        "Price": 1090,
        "ImageFile": "images/products/babolat-kitback-1.png",
        "Summary": "Puma Kit Bags for professionals.",
        "Types": {
            "Id": "63ca5d8849bc19321b8be5f1",
            "Name": "Kit Bags"
        },
        "Brands": {
            "Id": "63ca5e728c4cff9708ada2a6",
            "Name": "Puma"
        }
    },
    {
        "Id": "66b6a1310000000000000000",
        "Name": "Nike Shoes Shoe 5",
        "Description": "High quality Nike shoes built for comfort.",
        "Price": 3100,
        "ImageFile": "images/products/nike_shoe-5.png",
        "Summary": "Nike Shoes for professionals.",
        "Types": {
            "Id": "63ca5d4bc3a8a58f47299f97",
            "Name": "Shoes"
        },
        "Brands": {
            "Id": "63ca5e7ec90ff5c8f44d5ac8",
            "Name": "Nike"
        }
    },
    {
        "Id": "66b6a1320000000000000000",
        "Name": "Nike Shoes Shoe 6",
        "Description": "High quality Nike shoes lightweight and durable.",
        "Price": 3175,
        "ImageFile": "images/products/adidas_shoe-1.png",
        "Summary": "Nike Shoes for professionals.",
        "Types": {
            "Id": "63ca5d4bc3a8a58f47299f97",
            "Name": "Shoes"
        },
        "Brands": {
            "Id": "63ca5e7ec90ff5c8f44d5ac8",
            "Name": "Nike"
        }
    },
    {
        "Id": "66b6a1330000000000000000",
        "Name": "Nike Rackets Racket 5",
        "Description": "High quality Nike rackets for powerful shots.",
        "Price": 1700,
        "ImageFile": "images/products/babolat-racket-3.png",
        "Summary": "Nike Rackets for professionals.",
        "Types": {
            "Id": "63ca5d6d958e43ee1cd375fe",
            "Name": "Rackets"
        },
        "Brands": {
            "Id": "63ca5e7ec90ff5c8f44d5ac8",
            "Name": "Nike"
        }
    },
    {
        "Id": "66b6a1340000000000000000",
        "Name": "Nike Rackets Racket 6",
        "Description": "High quality Nike rackets for precision play.",
        "Price": 1775,
        "ImageFile": "images/products/babolat-racket-1.png",
        "Summary": "Nike Rackets for professionals.",
        "Types": {
            "Id": "63ca5d6d958e43ee1cd375fe",
            "Name": "Rackets"
        },
        "Brands": {
            "Id": "63ca5e7ec90ff5c8f44d5ac8",
            "Name": "Nike"
        }
    },
    {
        "Id": "66b6a1350000000000000000",
        "Name": "Nike Kit Bags Kit Bag 5",
        "Description": "High quality Nike kit bags spacious and stylish.",
        "Price": 1050,
        "ImageFile": "images/products/yonex-kitback-3.png",
        "Summary": "Nike Kit Bags for professionals.",
        "Types": {
            "Id": "63ca5d8849bc19321b8be5f1",
            "Name": "Kit Bags"
        },
        "Brands": {
            "Id": "63ca5e7ec90ff5c8f44d5ac8",
            "Name": "Nike"
        }
    },
    {
        "Id": "66b6a1360000000000000000",
        "Name": "Nike Kit Bags Kit Bag 6",
        "Description": "High quality Nike kit bags durable material.",
        "Price": 1125,
        "ImageFile": "images/products/yonex-kitback-3.png",
        "Summary": "Nike Kit Bags for professionals.",
        "Types": {
            "Id": "63ca5d8849bc19321b8be5f1",
            "Name": "Kit Bags"
        },
        "Brands": {
            "Id": "63ca5e7ec90ff5c8f44d5ac8",
            "Name": "Nike"
        }
    },
    {
        "Id": "66b6a1370000000000000000",
        "Name": "Babolat Shoes Shoe 6",
        "Description": "High quality Babolat shoes built for comfort.",
        "Price": 3160,
        "ImageFile": "images/products/babolat_shoe-1.png",
        "Summary": "Babolat Shoes for professionals.",
        "Types": {
            "Id": "63ca5d4bc3a8a58f47299f97",
            "Name": "Shoes"
        },
        "Brands": {
            "Id": "63ca5e8d6110a9c56ee7dc48",
            "Name": "Babolat"
        }
    },
    {
        "Id": "66b6a1380000000000000000",
        "Name": "Babolat Shoes Shoe 7",
        "Description": "High quality Babolat shoes lightweight and durable.",
        "Price": 3240,
        "ImageFile": "images/products/babolat_shoe-2.png",
        "Summary": "Babolat Shoes for professionals.",
        "Types": {
            "Id": "63ca5d4bc3a8a58f47299f97",
            "Name": "Shoes"
        },
        "Brands": {
            "Id": "63ca5e8d6110a9c56ee7dc48",
            "Name": "Babolat"
        }
    },
    {
        "Id": "66b6a1390000000000000000",
        "Name": "Babolat Rackets Racket 6",
        "Description": "High quality Babolat rackets for powerful shots.",
        "Price": 1740,
        "ImageFile": "images/products/babolat-racket-1.png",
        "Summary": "Babolat Rackets for professionals.",
        "Types": {
            "Id": "63ca5d6d958e43ee1cd375fe",
            "Name": "Rackets"
        },
        "Brands": {
            "Id": "63ca5e8d6110a9c56ee7dc48",
            "Name": "Babolat"
        }
    },
    {
        "Id": "66b6a1400000000000000000",
        "Name": "Babolat Rackets Racket 7",
        "Description": "High quality Babolat rackets for precision play.",
        "Price": 1820,
        "ImageFile": "images/products/babolat-racket-2.png",
        "Summary": "Babolat Rackets for professionals.",
        "Types": {
            "Id": "63ca5d6d958e43ee1cd375fe",
            "Name": "Rackets"
        },
        "Brands": {
            "Id": "63ca5e8d6110a9c56ee7dc48",
            "Name": "Babolat"
        }
    },
    {
        "Id": "66b6a1410000000000000000",
        "Name": "Babolat Kit Bags Kit Bag 6",
        "Description": "High quality Babolat kit bags spacious and stylish.",
        "Price": 1080,
        "ImageFile": "images/products/babolat-kitback-1.png",
        "Summary": "Babolat Kit Bags for professionals.",
        "Types": {
            "Id": "63ca5d8849bc19321b8be5f1",
            "Name": "Kit Bags"
        },
        "Brands": {
            "Id": "63ca5e8d6110a9c56ee7dc48",
            "Name": "Babolat"
        }
    },
    {
        "Id": "66b6a1420000000000000000",
        "Name": "Babolat Kit Bags Kit Bag 7",
        "Description": "High quality Babolat kit bags durable material.",
        "Price": 1160,
        "ImageFile": "images/products/babolat-kitback-2.png",
        "Summary": "Babolat Kit Bags for professionals.",
        "Types": {
            "Id": "63ca5d8849bc19321b8be5f1",
            "Name": "Kit Bags"
        },
        "Brands": {
            "Id": "63ca5e8d6110a9c56ee7dc48",
            "Name": "Babolat"
        }
    }
]